./.gitignore
./PKG-INFO
./README.md
./pyproject.toml
./vision_agents/plugins/twilio/__init__.py
./vision_agents/plugins/twilio/audio.py
./vision_agents/plugins/twilio/call_registry.py
./vision_agents/plugins/twilio/media_stream.py
./vision_agents/plugins/twilio/models.py
./vision_agents/plugins/twilio/utils.py
vision_agents/plugins/twilio/__init__.py
vision_agents/plugins/twilio/audio.py
vision_agents/plugins/twilio/call_registry.py
vision_agents/plugins/twilio/media_stream.py
vision_agents/plugins/twilio/models.py
vision_agents/plugins/twilio/utils.py
vision_agents_plugins_twilio-0.1.0.dist-info/METADATA
vision_agents_plugins_twilio-0.1.0.dist-info/WHEEL
vision_agents_plugins_twilio-0.1.0.dist-info/RECORD
