Metadata-Version: 2.4
Name: vision-agents-plugins-twilio
Version: 0.1.0
Summary: Twilio plugin for Vision Agents - Voice call integration with media streaming
Project-URL: Documentation, https://visionagents.ai/
Project-URL: Website, https://visionagents.ai/
Project-URL: Source, https://github.com/GetStream/Vision-Agents
License-Expression: MIT
Requires-Python: >=3.10
Requires-Dist: fastapi>=0.100.0
Requires-Dist: numpy>=1.24.0
Requires-Dist: twilio>=9.0.0
Requires-Dist: vision-agents
